burrowkv/__init__.py
burrowkv/burrowkv.py
tests/__init__.py
tests/test_burrowkv.py
burrowkv-0.0.4.dist-info/LICENSE
burrowkv-0.0.4.dist-info/METADATA
burrowkv-0.0.4.dist-info/WHEEL
burrowkv-0.0.4.dist-info/top_level.txt
burrowkv-0.0.4.dist-info/RECORD
