Metadata-Version: 2.1
Name: burrowkv
Version: 0.0.4
Summary: key-value store
Home-page: https://github.com/iunary/burrowkv
Author: Yusuf
Author-email: contact@yusuf.im
License: MIT
Keywords: key value store,kv,key-value
Platform: UNKNOWN
Classifier: Programming Language :: Python :: 3
Classifier: Operating System :: OS Independent
Requires-Python: >=3.8
License-File: LICENSE
